examples/__init__.py
examples/atr/__init__.py
examples/atr/data.py
examples/atr/graphs.py
examples/atr/model.py
examples/atr/params.py
examples/atr/scenario.py
examples/atr/test.py
examples/atr/datapipeline/__init__.py
examples/atr/datapipeline/datagenerator.py
examples/atr/datapipeline/decoderprocessor.py
examples/atr/datapipeline/loadprocessor.py
examples/atr/datapipeline/prepareprocessor.py
examples/atr/datapipeline/scale_to_height_processor.py
examples/howtos/__init__.py
examples/howtos/differenttrainandvalgraph/__init__.py
examples/howtos/differenttrainandvalgraph/graph.py
examples/howtos/differenttrainandvalgraph/test.py
examples/howtos/parametrizablelayer/__init__.py
examples/howtos/parametrizablelayer/mylayer.py
examples/howtos/parametrizablelayer/test.py
examples/howtos/polymorphicscenarios/__init__.py
examples/howtos/polymorphicscenarios/scenario.py
examples/howtos/polymorphicscenarios/test.py
examples/howtos/staticmodelparameters/__init__.py
examples/howtos/staticmodelparameters/scenario.py
examples/howtos/staticmodelparameters/test.py
examples/howtos/trainerpipelineparams/__init__.py
examples/howtos/trainerpipelineparams/scenario.py
examples/howtos/trainerpipelineparams/test.py
examples/imageclassification/__init__.py
examples/imageclassification/data.py
examples/imageclassification/graphs.py
examples/imageclassification/model.py
examples/imageclassification/params.py
examples/imageclassification/predictor.py
examples/imageclassification/scenario.py
examples/imageclassification/test.py
examples/imageclassification/datapipeline/__init__.py
examples/imageclassification/datapipeline/datagenerator.py
examples/imageclassification/datapipeline/indextoclassprocessor.py
examples/imageclassification/datapipeline/loadprocessor.py
examples/imageclassification/datapipeline/predictiondatagenerator.py
examples/imageclassification/datapipeline/preparesampleprocessor.py
examples/imageclassification/datapipeline/rescaleprocessor.py
examples/template/__init__.py
ocrd_fork_tfaip-1.2.7.dist-info/LICENSE
ocrd_fork_tfaip-1.2.7.dist-info/METADATA
ocrd_fork_tfaip-1.2.7.dist-info/WHEEL
ocrd_fork_tfaip-1.2.7.dist-info/entry_points.txt
ocrd_fork_tfaip-1.2.7.dist-info/top_level.txt
ocrd_fork_tfaip-1.2.7.dist-info/RECORD
