Metadata-Version: 2.1
Name: ocrd-fork-tfaip
Version: 1.2.7
Summary: Python-based research framework for developing, organizing, and deploying Deep Learning models powered by Tensorflow.
Home-page: https://github.com/bertsky/tfaip
Author: PLANET AI GmbH
Author-email: admin@planet-ai.de
Maintainer: bertsky
License: GPL-v3.0
Keywords: machine learning,tensorflow,framework
Requires-Python: >=3.7
License-File: LICENSE
Requires-Dist: ocrd-fork-adabelief-tf
Requires-Dist: dataclasses-json
Requires-Dist: GitPython
Requires-Dist: imageio
Requires-Dist: nptyping
Requires-Dist: opencv-python-headless
Requires-Dist: openpyxl
Requires-Dist: paiargparse==1.1.2
Requires-Dist: pandas
Requires-Dist: pillow
Requires-Dist: prettytable
Requires-Dist: python-Levenshtein
Requires-Dist: scikit-image
Requires-Dist: pooch==1.4.0
Requires-Dist: tensorflow<2.16.0,>=2.4.0
Requires-Dist: tensorflow-addons>=0.12.0
Requires-Dist: tqdm
Requires-Dist: typeguard
Requires-Dist: xlrd==1.2.0
Provides-Extra: devel
Requires-Dist: black==21.6b0; extra == "devel"
Requires-Dist: flake8; extra == "devel"
Requires-Dist: pre-commit; extra == "devel"
Requires-Dist: pytest; extra == "devel"
Requires-Dist: pytest-timeout; extra == "devel"
Requires-Dist: pytest-xdist; extra == "devel"
